{ "summary" : "A formal-parameter-list is a list of formal-parameters.", "ast" : "autumn.lang.compiler.ast.nodes.FormalParameterList", "syntax" : [[0, "( <i><a href=\"ConstructPage.html?construct=FormalParameter\">param</a><sub>1</sub></i> , ... , <i><a href=\"ConstructPage.html?construct=FormalParameter\">param</a><sub>n</sub></i> )"]], "details" : [], "static-checks" : [], "example-1" : ["module Main in execution;%0A%0A%0A/// This function has a formal-parameter-list with three elements. %0A///%0Adefun f (x : int, %0A         y : int, %0A         z : int) : int%0A{%0A    return x * y + z;%0A}%0A%0A@Start%0Adefun main (args : String[]) : void%0A{%0A    F::println(My::f(2, 3, 4));%0A    F::println(My::f(2, 3, 5));%0A    F::println(My::f(2, 3, 6));%0A    F::println(My::f(2, 3, 7));%0A}", "10%0A11%0A12%0A13"] }