[{ "test" : 139, "construct" : "autumn.lang.compiler.ast.nodes.AnnotationDefinition", "error-code" : "DUPLICATE_TYPE" }, { "test" : 150, "construct" : "autumn.lang.compiler.ast.nodes.AnnotationDefinition", "error-code" : "DUPLICATE_ANNOTATION" }, { "test" : 41, "construct" : "autumn.lang.compiler.ast.nodes.ExceptionDefinition", "error-code" : "DUPLICATE_TYPE" }, { "test" : 151, "construct" : "autumn.lang.compiler.ast.nodes.ExceptionDefinition", "error-code" : "DUPLICATE_ANNOTATION" }, { "test" : 43, "construct" : "autumn.lang.compiler.ast.nodes.ExceptionDefinition", "error-code" : "NO_SUCH_TYPE" }, { "test" : 44, "construct" : "autumn.lang.compiler.ast.nodes.ExceptionDefinition", "error-code" : "INACCESSIBLE_TYPE" }, { "test" : 138, "construct" : "autumn.lang.compiler.ast.nodes.ExceptionDefinition", "error-code" : "EXPECTED_CLASS_TYPE" }, { "test" : 42, "construct" : "autumn.lang.compiler.ast.nodes.ExceptionDefinition", "error-code" : "EXPECTED_THROWABLE" }, { "test" : 45, "construct" : "autumn.lang.compiler.ast.nodes.ExceptionDefinition", "error-code" : "CIRCULAR_INHERITANCE" }, { "test" : 46, "construct" : "autumn.lang.compiler.ast.nodes.ExceptionDefinition", "error-code" : "CIRCULAR_INHERITANCE" }, { "test" : 49, "construct" : "autumn.lang.compiler.ast.nodes.EnumDefinition", "error-code" : "DUPLICATE_TYPE" }, { "test" : 152, "construct" : "autumn.lang.compiler.ast.nodes.EnumDefinition", "error-code" : "DUPLICATE_ANNOTATION" }, { "test" : 50, "construct" : "autumn.lang.compiler.ast.nodes.EnumDefinition", "error-code" : "DUPLICATE_ELEMENT" }, { "test" : 168, "construct" : "autumn.lang.compiler.ast.nodes.DesignDefinition", "error-code" : "DUPLICATE_TYPE" }, { "test" : 153, "construct" : "autumn.lang.compiler.ast.nodes.DesignDefinition", "error-code" : "DUPLICATE_ANNOTATION" }, { "test" : 170, "construct" : "autumn.lang.compiler.ast.nodes.DesignDefinition", "error-code" : "NO_SUCH_TYPE" }, { "test" : 171, "construct" : "autumn.lang.compiler.ast.nodes.DesignDefinition", "error-code" : "INACCESSIBLE_TYPE" }, { "test" : 178, "construct" : "autumn.lang.compiler.ast.nodes.DesignDefinition", "error-code" : "DUPLICATE_SUPERTYPE" }, { "test" : 181, "construct" : "autumn.lang.compiler.ast.nodes.DesignDefinition", "error-code" : "EXPECTED_INTERFACE_TYPE" }, { "test" : 173, "construct" : "autumn.lang.compiler.ast.nodes.DesignDefinition", "error-code" : "EXPECTED_INTERFACE_TYPE" }, { "test" : 172, "construct" : "autumn.lang.compiler.ast.nodes.DesignDefinition", "error-code" : "EXPECTED_INTERFACE_TYPE" }, { "test" : 180, "construct" : "autumn.lang.compiler.ast.nodes.DesignDefinition", "error-code" : "EXPECTED_DESIGN_TYPE" }, { "test" : 174, "construct" : "autumn.lang.compiler.ast.nodes.DesignDefinition", "error-code" : "DUPLICATE_ELEMENT" }, { "test" : 175, "construct" : "autumn.lang.compiler.ast.nodes.DesignDefinition", "error-code" : "NO_SUCH_TYPE" }, { "test" : 176, "construct" : "autumn.lang.compiler.ast.nodes.DesignDefinition", "error-code" : "INACCESSIBLE_TYPE" }, { "test" : 177, "construct" : "autumn.lang.compiler.ast.nodes.DesignDefinition", "error-code" : "EXPECTED_VARIABLE_TYPE" }, { "test" : 179, "construct" : "autumn.lang.compiler.ast.nodes.DesignDefinition", "error-code" : "COVARIANCE_VIOLATION" }, { "test" : 162, "construct" : "autumn.lang.compiler.ast.nodes.DesignDefinition", "error-code" : "CIRCULAR_INHERITANCE" }, { "test" : 163, "construct" : "autumn.lang.compiler.ast.nodes.DesignDefinition", "error-code" : "CIRCULAR_INHERITANCE" }, { "test" : 121, "construct" : "autumn.lang.compiler.ast.nodes.StructDefinition", "error-code" : "DUPLICATE_TYPE" }, { "test" : 155, "construct" : "autumn.lang.compiler.ast.nodes.StructDefinition", "error-code" : "DUPLICATE_ANNOTATION" }, { "test" : 122, "construct" : "autumn.lang.compiler.ast.nodes.StructDefinition", "error-code" : "NO_SUCH_TYPE" }, { "test" : 123, "construct" : "autumn.lang.compiler.ast.nodes.StructDefinition", "error-code" : "INACCESSIBLE_TYPE" }, { "test" : 124, "construct" : "autumn.lang.compiler.ast.nodes.StructDefinition", "error-code" : "DUPLICATE_SUPERTYPE" }, { "test" : 191, "construct" : "autumn.lang.compiler.ast.nodes.StructDefinition", "error-code" : "EXPECTED_INTERFACE_TYPE" }, { "test" : 192, "construct" : "autumn.lang.compiler.ast.nodes.StructDefinition", "error-code" : "EXPECTED_DESIGN_TYPE" }, { "test" : 125, "construct" : "autumn.lang.compiler.ast.nodes.StructDefinition", "error-code" : "DUPLICATE_ELEMENT" }, { "test" : 193, "construct" : "autumn.lang.compiler.ast.nodes.StructDefinition", "error-code" : "NO_SUCH_TYPE" }, { "test" : 194, "construct" : "autumn.lang.compiler.ast.nodes.StructDefinition", "error-code" : "INACCESSIBLE_TYPE" }, { "test" : 195, "construct" : "autumn.lang.compiler.ast.nodes.StructDefinition", "error-code" : "EXPECTED_VARIABLE_TYPE" }, { "test" : 164, "construct" : "autumn.lang.compiler.ast.nodes.StructDefinition", "error-code" : "CIRCULAR_INHERITANCE" }, { "test" : 169, "construct" : "autumn.lang.compiler.ast.nodes.TupleDefinition", "error-code" : "DUPLICATE_TYPE" }, { "test" : 196, "construct" : "autumn.lang.compiler.ast.nodes.TupleDefinition", "error-code" : "NO_SUCH_TYPE" }, { "test" : 197, "construct" : "autumn.lang.compiler.ast.nodes.TupleDefinition", "error-code" : "INACCESSIBLE_TYPE" }, { "test" : 198, "construct" : "autumn.lang.compiler.ast.nodes.TupleDefinition", "error-code" : "EXPECTED_INTERFACE_TYPE" }, { "test" : 199, "construct" : "autumn.lang.compiler.ast.nodes.TupleDefinition", "error-code" : "EXPECTED_DESIGN_TYPE" }, { "test" : 200, "construct" : "autumn.lang.compiler.ast.nodes.TupleDefinition", "error-code" : "DUPLICATE_SUPERTYPE" }, { "test" : 201, "construct" : "autumn.lang.compiler.ast.nodes.TupleDefinition", "error-code" : "DUPLICATE_ELEMENT" }, { "test" : 202, "construct" : "autumn.lang.compiler.ast.nodes.TupleDefinition", "error-code" : "NO_SUCH_TYPE" }, { "test" : 203, "construct" : "autumn.lang.compiler.ast.nodes.TupleDefinition", "error-code" : "INACCESSIBLE_TYPE" }, { "test" : 204, "construct" : "autumn.lang.compiler.ast.nodes.TupleDefinition", "error-code" : "EXPECTED_VARIABLE_TYPE" }, { "test" : 205, "construct" : "autumn.lang.compiler.ast.nodes.TupleDefinition", "error-code" : "COVARIANCE_VIOLATION" }, { "test" : 166, "construct" : "autumn.lang.compiler.ast.nodes.TupleDefinition", "error-code" : "CIRCULAR_INHERITANCE" }, { "test" : 139, "construct" : "autumn.lang.compiler.ast.nodes.FunctorDefinition", "error-code" : "DUPLICATE_TYPE" }, { "test" : 156, "construct" : "autumn.lang.compiler.ast.nodes.FunctorDefinition", "error-code" : "DUPLICATE_ANNOTATION" }, { "test" : 140, "construct" : "autumn.lang.compiler.ast.nodes.FunctorDefinition", "error-code" : "NO_SUCH_TYPE" }, { "test" : 141, "construct" : "autumn.lang.compiler.ast.nodes.FunctorDefinition", "error-code" : "INACCESSIBLE_TYPE" }, { "test" : 142, "construct" : "autumn.lang.compiler.ast.nodes.FunctorDefinition", "error-code" : "EXPECTED_CLASS_TYPE" }, { "test" : 143, "construct" : "autumn.lang.compiler.ast.nodes.FunctorDefinition", "error-code" : "EXPECTED_DEFINED_FUNCTOR_TYPE" }, { "test" : 144, "construct" : "autumn.lang.compiler.ast.nodes.FunctorDefinition", "error-code" : "NO_SUCH_TYPE" }, { "test" : 145, "construct" : "autumn.lang.compiler.ast.nodes.FunctorDefinition", "error-code" : "INACCESSIBLE_TYPE" }, { "test" : 146, "construct" : "autumn.lang.compiler.ast.nodes.FunctorDefinition", "error-code" : "EXPECTED_VARIABLE_TYPE" }, { "test" : 147, "construct" : "autumn.lang.compiler.ast.nodes.FunctorDefinition", "error-code" : "NO_SUCH_TYPE" }, { "test" : 148, "construct" : "autumn.lang.compiler.ast.nodes.FunctorDefinition", "error-code" : "INACCESSIBLE_TYPE" }, { "test" : 149, "construct" : "autumn.lang.compiler.ast.nodes.FunctorDefinition", "error-code" : "CIRCULAR_INHERITANCE" }, { "test" : 157, "construct" : "autumn.lang.compiler.ast.nodes.FunctionDefinition", "error-code" : "DUPLICATE_ANNOTATION" }, { "test" : 182, "construct" : "autumn.lang.compiler.ast.nodes.FunctionDefinition", "error-code" : "NO_SUCH_TYPE" }, { "test" : 183, "construct" : "autumn.lang.compiler.ast.nodes.FunctionDefinition", "error-code" : "INACCESSIBLE_TYPE" }, { "test" : 184, "construct" : "autumn.lang.compiler.ast.nodes.FunctionDefinition", "error-code" : "EXPECTED_VARIABLE_TYPE" }, { "test" : 185, "construct" : "autumn.lang.compiler.ast.nodes.FunctionDefinition", "error-code" : "NO_SUCH_TYPE" }, { "test" : 186, "construct" : "autumn.lang.compiler.ast.nodes.FunctionDefinition", "error-code" : "INACCESSIBLE_TYPE" }, { "test" : 1, "construct" : "autumn.lang.compiler.ast.nodes.IfStatement", "error-code" : "EXPECTED_CONDITION" }, { "test" : 2, "construct" : "autumn.lang.compiler.ast.nodes.IfStatement", "error-code" : "EXPECTED_CONDITION" }, { "test" : 10, "construct" : "autumn.lang.compiler.ast.nodes.WhenStatement", "error-code" : "EXPECTED_CONDITION" }, { "test" : 21, "construct" : "autumn.lang.compiler.ast.nodes.GotoStatement", "error-code" : "NO_SUCH_LABEL" }, { "test" : 21, "construct" : "autumn.lang.compiler.ast.nodes.MarkerStatement", "error-code" : "DUPLICATE_LABEL" }, { "test" : 126, "construct" : "autumn.lang.compiler.ast.nodes.BranchStatement", "error-code" : "EXPECTED_INTEGER" }, { "test" : 127, "construct" : "autumn.lang.compiler.ast.nodes.BranchStatement", "error-code" : "NO_SUCH_LABEL" }, { "test" : 128, "construct" : "autumn.lang.compiler.ast.nodes.BranchStatement", "error-code" : "NO_SUCH_LABEL" }, { "test" : 3, "construct" : "autumn.lang.compiler.ast.nodes.WhileStatement", "error-code" : "EXPECTED_CONDITION" }, { "test" : 4, "construct" : "autumn.lang.compiler.ast.nodes.UntilStatement", "error-code" : "EXPECTED_CONDITION" }, { "test" : 5, "construct" : "autumn.lang.compiler.ast.nodes.DoWhileStatement", "error-code" : "EXPECTED_CONDITION" }, { "test" : 6, "construct" : "autumn.lang.compiler.ast.nodes.DoUntilStatement", "error-code" : "EXPECTED_CONDITION" }, { "test" : 56, "construct" : "autumn.lang.compiler.ast.nodes.ForStatement", "error-code" : "DUPLICATE_VARIABLE" }, { "test" : 57, "construct" : "autumn.lang.compiler.ast.nodes.ForStatement", "error-code" : "EXPECTED_INTEGER" }, { "test" : 58, "construct" : "autumn.lang.compiler.ast.nodes.ForStatement", "error-code" : "EXPECTED_INTEGER" }, { "test" : 59, "construct" : "autumn.lang.compiler.ast.nodes.ForStatement", "error-code" : "EXPECTED_CONDITION" }, { "test" : 69, "construct" : "autumn.lang.compiler.ast.nodes.ForStatement", "error-code" : "VARIABLE_OUTSIDE_OF_SCOPE" }, { "test" : 70, "construct" : "autumn.lang.compiler.ast.nodes.ForStatement", "error-code" : "VARIABLE_OUTSIDE_OF_SCOPE" }, { "test" : 60, "construct" : "autumn.lang.compiler.ast.nodes.BreakStatement", "error-code" : "BREAK_OUTSIDE_OF_LOOP" }, { "test" : 73, "construct" : "autumn.lang.compiler.ast.nodes.ContinueStatement", "error-code" : "CONTINUE_OUTSIDE_OF_LOOP" }, { "test" : 74, "construct" : "autumn.lang.compiler.ast.nodes.RedoStatement", "error-code" : "REDO_OUTSIDE_OF_LOOP" }, { "test" : 15, "construct" : "autumn.lang.compiler.ast.nodes.VarStatement", "error-code" : "DUPLICATE_VARIABLE" }, { "test" : 16, "construct" : "autumn.lang.compiler.ast.nodes.ValStatement", "error-code" : "DUPLICATE_VARIABLE" }, { "test" : 17, "construct" : "autumn.lang.compiler.ast.nodes.LetStatement", "error-code" : "NO_SUCH_VARIABLE" }, { "test" : 11, "construct" : "autumn.lang.compiler.ast.nodes.TryCatchStatement", "error-code" : "DUPLICATE_VARIABLE" }, { "test" : 12, "construct" : "autumn.lang.compiler.ast.nodes.TryCatchStatement", "error-code" : "EXPECTED_THROWABLE" }, { "test" : 13, "construct" : "autumn.lang.compiler.ast.nodes.TryCatchStatement", "error-code" : "DUPLICATE_EXCEPTION_HANDLER" }, { "test" : 14, "construct" : "autumn.lang.compiler.ast.nodes.TryCatchStatement", "error-code" : "NO_SUCH_TYPE" }, { "test" : 72, "construct" : "autumn.lang.compiler.ast.nodes.TryCatchStatement", "error-code" : "INACCESSIBLE_TYPE" }, { "test" : 71, "construct" : "autumn.lang.compiler.ast.nodes.TryCatchStatement", "error-code" : "VARIABLE_OUTSIDE_OF_SCOPE" }, { "test" : 10, "construct" : "autumn.lang.compiler.ast.nodes.ThrowStatement", "error-code" : "EXPECTED_THROWABLE" }, { "test" : 7, "construct" : "autumn.lang.compiler.ast.nodes.AssertStatement", "error-code" : "EXPECTED_CONDITION" }, { "test" : 8, "construct" : "autumn.lang.compiler.ast.nodes.AssertStatement", "error-code" : "EXPECTED_CONDITION" }, { "test" : 9, "construct" : "autumn.lang.compiler.ast.nodes.AssertStatement", "error-code" : "EXPECTED_STRING" }]