{ "group" : "Iterables", "summary" : "This function creates an iterable whose iterator iterates over a functor.", "signature" : "iter (input : <a href='http://mackenzie-high.github.io/autumn/javadoc/autumn/util/functors/Function0.html'>Function0</a>) : <a href='https://docs.oracle.com/javase/7/docs/api/java/lang/Iterable.html'>Iterable</a>", "formals" : [["input", "class autumn.util.functors.Function0", "is the functor itself."]], "returns" : ["<a href='https://docs.oracle.com/javase/7/docs/api/java/lang/Iterable.html'>Iterable</a>", "The aforedescribed iterable is returned."], "throws" : [["<a href='https://docs.oracle.com/javase/7/docs/api/java/lang/NullPointerException.html'>NullPointerException</a>", "if <i>input</i> is null."]], "details" : [] }