{ "group" : "Operators", "summary" : "This function is a dynamically dispatched equivalent of the multiplication operator.", "signature" : "operationMultiply null : <a href='https://docs.oracle.com/javase/7/docs/api/java/lang/Object.html'>Object</a>", "formals" : [["left", "class java.lang.Object", "is the left operand."], ["right", "class java.lang.Object", "is the right operand."]], "returns" : ["<a href='https://docs.oracle.com/javase/7/docs/api/java/lang/Object.html'>Object</a>", "Return the result of the operation."], "throws" : [], "details" : [] }