{ "group" : "Math", "summary" : "This is the tangent function.", "signature" : "tan (angle : double) : double", "formals" : [["angle", "double", "is the angle in radians."]], "returns" : ["double", "tan(angle)"], "throws" : [], "details" : [], "example-1" : ["module Main in examples;%0A%0A@Start%0Adefun main (args : String[]) : void%0A{%0A    val case1 = false & false;%0A    val case2 = false & true;%0A    val case3 = true & false;%0A    val case4 = true & true;%0A%0A    F::println(%22Truth Table:%22);%0A    F::println(%22  F & F = %22 .. case1);%0A    F::println(%22  F & T = %22 .. case2);%0A    F::println(%22  T & F = %22 .. case3);%0A    F::println(%22  T & T = %22 .. case4);%0A%0A    F::println();%0A%0A    F::println(%22Short Circuit:%22);%0A    My::sc(false, false);%0A    My::sc(false, true);%0A    My::sc(true, false);%0A    My::sc(true, true);%0A}%0A%0Adefun sc(left : boolean, right : boolean) : void%0A{%0A    F::print(%22  %22);%0A    My::operand1(left) & My::operand2(left);%0A    F::println();%0A}%0A%0Adefun operand1(value : boolean) : boolean%0A{%0A    F::print(%22L%22);%0A    return value;%0A}%0A%0Adefun operand2(value : boolean) : boolean%0A{%0A    F::print(%22R%22);%0A    return value;%0A}", "Truth Table:%0A  F & F = false%0A  F & T = false%0A  T & F = false%0A  T & T = true%0A%0AShort Circuit:%0A  L%0A  L%0A  LR%0A  LR"] }